plone.rest-5.1.0-py3.12-nspkg.pth
plone/rest/__init__.py
plone/rest/configure.zcml
plone/rest/cors.py
plone/rest/demo.py
plone/rest/errors.py
plone/rest/events.py
plone/rest/explicitacquisition.py
plone/rest/interfaces.py
plone/rest/meta.zcml
plone/rest/negotiation.py
plone/rest/patches.py
plone/rest/patches.zcml
plone/rest/service.py
plone/rest/testing.py
plone/rest/testing.zcml
plone/rest/traverse.py
plone/rest/zcml.py
plone/rest/tests/__init__.py
plone/rest/tests/file.pdf
plone/rest/tests/image.png
plone/rest/tests/test_cors.py
plone/rest/tests/test_dexterity.py
plone/rest/tests/test_dispatching.py
plone/rest/tests/test_error_handling.py
plone/rest/tests/test_explicitacquisition.py
plone/rest/tests/test_named_services.py
plone/rest/tests/test_negotiation.py
plone/rest/tests/test_permissions.py
plone/rest/tests/test_redirects.py
plone/rest/tests/test_siteroot.py
plone/rest/tests/test_traversal.py
plone_rest-5.1.0.dist-info/METADATA
plone_rest-5.1.0.dist-info/WHEEL
plone_rest-5.1.0.dist-info/entry_points.txt
plone_rest-5.1.0.dist-info/namespace_packages.txt
plone_rest-5.1.0.dist-info/top_level.txt
plone_rest-5.1.0.dist-info/RECORD
