Metadata-Version: 2.4
Name: plone.rest
Version: 5.1.0
Summary: Plone support for HTTP verbs.
Home-page: https://github.com/plone/plone.rest/
Author: Plone Foundation
Author-email: plone-developers@lists.sourceforge.net
License: GPL version 2
Keywords: rest http
Classifier: Development Status :: 5 - Production/Stable
Classifier: Environment :: Web Environment
Classifier: Framework :: Plone
Classifier: Framework :: Plone :: 6.0
Classifier: Framework :: Plone :: 6.1
Classifier: Framework :: Plone :: Core
Classifier: Framework :: Zope2
Classifier: Framework :: Zope :: 5
Classifier: License :: OSI Approved :: GNU General Public License (GPL)
Classifier: Operating System :: OS Independent
Classifier: Programming Language :: Python
Classifier: Programming Language :: Python :: 3.8
Classifier: Programming Language :: Python :: 3.9
Classifier: Programming Language :: Python :: 3.10
Classifier: Programming Language :: Python :: 3.11
Classifier: Programming Language :: Python :: 3.12
Classifier: Programming Language :: Python :: 3.13
Classifier: Programming Language :: Python :: 3 :: Only
Classifier: Topic :: Software Development :: Libraries :: Python Modules
Requires-Python: >=3.8
Requires-Dist: setuptools
Requires-Dist: collective.monkeypatcher
Requires-Dist: Products.CMFCore
Requires-Dist: Zope
Requires-Dist: plone.memoize
Requires-Dist: zope.browserpage
Provides-Extra: test
Requires-Dist: plone.app.testing[robot]>=4.2.2; extra == "test"
Requires-Dist: requests; extra == "test"
Requires-Dist: BTrees; extra == "test"
Requires-Dist: plone.app.contenttypes[test]; extra == "test"
Requires-Dist: plone.app.redirector; extra == "test"
Requires-Dist: plone.app.textfield; extra == "test"
Requires-Dist: plone.namedfile; extra == "test"
Requires-Dist: plone.testing; extra == "test"
Requires-Dist: z3c.relationfield; extra == "test"
Requires-Dist: zope.intid; extra == "test"
Dynamic: author
Dynamic: author-email
Dynamic: classifier
Dynamic: description
Dynamic: home-page
Dynamic: keywords
Dynamic: license
Dynamic: provides-extra
Dynamic: requires-dist
Dynamic: requires-python
Dynamic: summary
